dwriteshapepy/__init__.py
dwriteshapepy/__main__.py
dwriteshapepy/dwriteshape.cp313-win_amd64.pyd
dwriteshapepy-1.0.12.dist-info/METADATA
dwriteshapepy-1.0.12.dist-info/NOTICE.txt
dwriteshapepy-1.0.12.dist-info/WHEEL
dwriteshapepy-1.0.12.dist-info/entry_points.txt
dwriteshapepy-1.0.12.dist-info/top_level.txt
dwriteshapepy-1.0.12.dist-info/RECORD
