Metadata-Version: 2.2
Name: dwriteshapepy
Version: 1.0.12
Summary: Python extension for Windows DirectWrite shaping, modeled after uharfbuzz 
Home-page: https://github.com/microsoft/DWriteShapePy
Author: Paul Linnerud
Author-email: paulli@microsoft.com
License: MIT
Classifier: Programming Language :: Python :: 3
Classifier: License :: OSI Approved :: MIT License
Classifier: Operating System :: Microsoft :: Windows :: Windows 10
Requires-Python: >=3.9
License-File: src/NOTICE.txt
Dynamic: author
Dynamic: author-email
Dynamic: classifier
Dynamic: home-page
Dynamic: license
Dynamic: requires-python
Dynamic: summary
